MANIFEST.in
README.md
setup.py
MSCSol/__init__.py
MSCSol/data_process.py
MSCSol.egg-info/PKG-INFO
MSCSol.egg-info/SOURCES.txt
MSCSol.egg-info/dependency_links.txt
MSCSol.egg-info/top_level.txt
MSCSol/gvp/MSCSolmodel.py
MSCSol/gvp/__init__.py
MSCSol/gvp/SKANet/SKAnet.py
MSCSol/gvp/SKANet/__init__.py
MSCSol/gvp/SKANet/features.py
MSCSol/gvp/SKANet/helpers.py
MSCSol/gvp/SKANet/registry.py
MSCSol/gvp/SKANet/resnet.py
MSCSol/gvp/SKANet/config/__init__.py
MSCSol/gvp/SKANet/config/constants.py
MSCSol/gvp/SKANet/layers/__init__.py
MSCSol/gvp/SKANet/layers/activations.py
MSCSol/gvp/SKANet/layers/activations_jit.py
MSCSol/gvp/SKANet/layers/activations_me.py
MSCSol/gvp/SKANet/layers/adaptive_avgmax_pool.py
MSCSol/gvp/SKANet/layers/anti_aliasing.py
MSCSol/gvp/SKANet/layers/blur_pool.py
MSCSol/gvp/SKANet/layers/cbam.py
MSCSol/gvp/SKANet/layers/classifier.py
MSCSol/gvp/SKANet/layers/cond_conv2d.py
MSCSol/gvp/SKANet/layers/config.py
MSCSol/gvp/SKANet/layers/conv2d_same.py
MSCSol/gvp/SKANet/layers/conv_bn_act.py
MSCSol/gvp/SKANet/layers/create_act.py
MSCSol/gvp/SKANet/layers/create_attn.py
MSCSol/gvp/SKANet/layers/create_conv2d.py
MSCSol/gvp/SKANet/layers/create_norm_act.py
MSCSol/gvp/SKANet/layers/drop.py
MSCSol/gvp/SKANet/layers/eca.py
MSCSol/gvp/SKANet/layers/evo_norm.py
MSCSol/gvp/SKANet/layers/helpers.py
MSCSol/gvp/SKANet/layers/inplace_abn.py
MSCSol/gvp/SKANet/layers/kerv2d.py
MSCSol/gvp/SKANet/layers/median_pool.py
MSCSol/gvp/SKANet/layers/mixed_conv2d.py
MSCSol/gvp/SKANet/layers/mlp.py
MSCSol/gvp/SKANet/layers/norm_act.py
MSCSol/gvp/SKANet/layers/padding.py
MSCSol/gvp/SKANet/layers/patch_embed.py
MSCSol/gvp/SKANet/layers/pool2d_same.py
MSCSol/gvp/SKANet/layers/se.py
MSCSol/gvp/SKANet/layers/selective_kernel.py
MSCSol/gvp/SKANet/layers/separable_conv.py
MSCSol/gvp/SKANet/layers/shiftlution.py
MSCSol/gvp/SKANet/layers/space_to_depth.py
MSCSol/gvp/SKANet/layers/split_attn.py
MSCSol/gvp/SKANet/layers/split_batchnorm.py
MSCSol/gvp/SKANet/layers/std_conv.py
MSCSol/gvp/SKANet/layers/tbconv.py
MSCSol/gvp/SKANet/layers/weight_init.py