Metadata-Version: 2.1
Name: MSCSol
Version: 1.0.0
Summary: A tool for predicting the solubility of small molecule drugs.
Home-page: https://github.com/ZiyuFanCSU/MSCSol
Author: Ziyu Fan
Author-email: fzy_csu@qq.com
